unlimited_machine_translator/__init__.py
unlimited_machine_translator/translator.py
unlimited_machine_translator-1.1.8.dist-info/LICENSE
unlimited_machine_translator-1.1.8.dist-info/METADATA
unlimited_machine_translator-1.1.8.dist-info/WHEEL
unlimited_machine_translator-1.1.8.dist-info/top_level.txt
unlimited_machine_translator-1.1.8.dist-info/RECORD
